vizarr/__init__.py
vizarr/_widget.js
vizarr/_widget.py
vizarr-0.1.1.dist-info/METADATA
vizarr-0.1.1.dist-info/WHEEL
vizarr-0.1.1.dist-info/RECORD
